fuzzy/__init__.py
fuzzy/logic/__init__.py
fuzzy/logic/knowledge_base.py
fuzzy/logic/rule.py
fuzzy/logic/rulebase.py
fuzzy/logic/variables.py
fuzzy/logic/control/__init__.py
fuzzy/logic/control/controller.py
fuzzy/logic/control/defuzzification.py
fuzzy/logic/control/configurations/__init__.py
fuzzy/logic/control/configurations/abstract.py
fuzzy/logic/control/configurations/data.py
fuzzy/logic/control/configurations/impl.py
fuzzy/relations/__init__.py
fuzzy/relations/aggregation.py
fuzzy/relations/compound.py
fuzzy/relations/linkage.py
fuzzy/relations/n_ary.py
fuzzy/relations/t_norm.py
fuzzy/sets/__init__.py
fuzzy/sets/abstract.py
fuzzy/sets/group.py
fuzzy/sets/membership.py
fuzzy/sets/impl/__init__.py
fuzzy/sets/impl/cmf.py
fuzzy/sets/impl/dmf.py
fuzzy/utils/__init__.py
fuzzy/utils/classes.py
fuzzy/utils/functions.py
fuzzy_theory-0.0.7.dist-info/METADATA
fuzzy_theory-0.0.7.dist-info/WHEEL
fuzzy_theory-0.0.7.dist-info/licenses/LICENSE
fuzzy_theory-0.0.7.dist-info/RECORD
