Metadata-Version: 2.4
Name: fuzzy-theory
Version: 0.0.7
Summary: The fuzzy-theory library provides a PyTorch interface to fuzzy set theory and fuzzy logic operations.
Project-URL: Homepage, https://github.com/johnHostetter/fuzzy-theory
Project-URL: Issues, https://github.com/johnHostetter/fuzzy-theory/issues
Author-email: John Wesley Hostetter <jhostetter16@gmail.com>
License-File: LICENSE
Classifier: License :: OSI Approved :: MIT License
Classifier: Operating System :: OS Independent
Classifier: Programming Language :: Python :: 3
Requires-Python: >=3.9
